{
    "pedagogical": [
        {
            "title": "Bucles while.",
            "blocks": [
                {
                    "type": "info",
                    "text": "También puede usar otras declaraciones, como declaraciones if en bucles.\nEsto es especialmente útil en cosas como los juegos, en los que es posible que deba\nrecorrer varias acciones del jugador y agregar o quitar puntos a la puntuación del\njugador.\n\nMira este código, que usa una instrucción if/else dentro de un ciclo while para separar\nlos números pares e impares en el rango de 1 a 10:"
                },
                {
                    "type": "Consola",
                    "text": "x = 1\nwhile x < 10:\n  if x%2 == 0:\n    print(str(x) + ' is even')\n  else:\n    print(str(x) + ' is odd')\n  x += 1"
                },
                {
                    "type": "hint",
                    "text": "str(x) se usa para convertir el número x en una cadena, de modo que pueda usarse para la concatenación."
                }
            ]
        }
    ],
    "draganddrop": [
        {
            "title": "Selecciona la respuesta correcta.",
            "multipleResponses": true,
            "draganddropSecuence": true,
            "blocks": [
                {
                    "type": "info",
                    "text": "Complete los espacios en blanco para crear un bucle que incremente el valor de x en 2 e imprima los valores pares."
                },
                {
                    "type": "Consola",
                    "text": "x = 0\n___ x <= 20___\n   ___(X)\n   x + = 2"
                }
            ],
            "answers": [
                {
                    "text": ":"
                },
                {
                    "text": "print"
                },
                {
                    "text": "while"
                }
            ],
            "correctOrder": ["while",":","print"]
        }
    ]
}