{
    "pedagogical": [
        {
            "title": "Input con numero",
            "blocks": [
                {
                    "type": "info",
                    "text": "Entonces sabemos que la función input() devuelve una cadena. Pero, ¿y si necesitamos que sea otra cosa, como un número? No hay problema, ¡podemos hacerlo totalmente!\n\nSupongamos que hemos tomado la edad del usuario como entrada. Para convertirlo a un número, podemos usar la función int() :"
                },
                {
                    "type": "Consola",
                    "text": "Código de Python:\n\nage = int(input())\nprint(age)\n>?"
                },
                {
                    "type": "hint",
                    "text": "Esto lo convertirá de una cadena a un número entero. Sencillo, ¿verdad?"
                }
            ]
        }
    ],

    "pedagogical2": [
        {
            "title": "Entrada del usuario",
            "blocks": [
                {
                    "type": "info",
                    "text": "El comando input () le pide al usuario que ingrese y devuelve lo que ingresa como una cadena. Como esto:"
                },
                {
                    "type": "Consola",
                    "text": "Código de Python:\n\nx = input()\nprint(x)\n>?"
                }
            ]
        }
    ]
}
