{
    "quizzes": [
        {
            "module": 1,
            "quiz_number": 1,
            "sections": [
                {
                    "type": "JsonWindow",
                    "filename": "M1_Q1_Main.json",
                    "page_type": "multiplechoice"
                },
                {
                    "type": "JsonWindow",
                    "filename": "M1_Q1_Main.json",
                    "page_type": "draganddrop"
                }
            ]
        },
        {
            "module": 1,
            "quiz_number": 2,
            "sections": [
                {
                    "type": "JsonWindow",
                    "filename": "M1_Q2_Main.json",
                    "page_type": "draganddrop"
                },
                {
                    "type": "JsonWindow",
                    "filename": "M1_Q2_Main.json",
                    "page_type": "multiplechoice"
                }
            ]
        },
        {
            "module": 2,
            "quiz_number": 1,
            "sections": [
                {
                    "type": "JsonWindow",
                    "filename": "M2_Q1_Main.json",
                    "page_type": "multiplechoice"
                },
                {
                    "type": "JsonWindow",
                    "filename": "M2_Q1_Main.json",
                    "page_type": "completeblankspace"
                }
            ]
        },
        {
            "module": 2,
            "quiz_number": 2,
            "sections": [
                {
                    "type": "JsonWindow",
                    "filename": "M2_Q2_Main.json",
                    "page_type": "multiplechoice"
                },
                {
                    "type": "JsonWindow",
                    "filename": "M2_Q2_Main.json",
                    "page_type": "draganddrop"
                }
            ]
        },
        {
            "module": 3,
            "quiz_number": 1,
            "sections": [
                {
                    "type": "JsonWindow",
                    "filename": "M3_Q1_Main.json",
                    "page_type": "multiplechoice"
                },
                {
                    "type": "JsonWindow",
                    "filename": "M3_Q1_Main.json",
                    "page_type": "completeblankspace"
                }
            ]
        },
        {
            "module": 3,
            "quiz_number": 2,
            "sections": [
                {
                    "type": "JsonWindow",
                    "filename": "M3_Q2_Main.json",
                    "page_type": "draganddrop"
                },
                {
                    "type": "JsonWindow",
                    "filename": "M3_Q2_Main.json",
                    "page_type": "multiplechoice"
                }
            ]
        },
        {
            "module": 4,
            "quiz_number": 1,
            "sections": [
                {
                    "type": "JsonWindow",
                    "filename": "M4_Q1_Main.json",
                    "page_type": "multiplechoice"
                },
                {
                    "type": "JsonWindow",
                    "filename": "M4_Q1_Main.json",
                    "page_type": "draganddrop"
                }
            ]
        },
        {
            "module": 4,
            "quiz_number": 2,
            "sections": [
                {
                    "type": "JsonWindow",
                    "filename": "M4_Q2_Main.json",
                    "page_type": "multiplechoice"
                },
                {
                    "type": "JsonWindow",
                    "filename": "M4_Q2_Main.json",
                    "page_type": "completeblankspace"
                }
            ]
        },
        {
            "module": 5,
            "quiz_number": 1,
            "sections": [
                {
                    "type": "JsonWindow",
                    "filename": "M5_Q1_Main.json",
                    "page_type": "multiplechoice"
                },
                {
                    "type": "JsonWindow",
                    "filename": "M5_Q1_Main.json",
                    "page_type": "draganddrop"
                }
            ]
        },
        {
            "module": 5,
            "quiz_number": 2,
            "sections": [
                {
                    "type": "JsonWindow",
                    "filename": "M5_Q2_Main.json",
                    "page_type": "multiplechoice"
                },
                {
                    "type": "JsonWindow",
                    "filename": "M5_Q2_Main.json",
                    "page_type": "draganddrop"
                }
            ]
        }
    ]
}
